collective.casestudy-1.0.0a3-py3.10-nspkg.pth
collective/casestudy/__init__.py
collective/casestudy/configure.zcml
collective/casestudy/interfaces.py
collective/casestudy/permissions.zcml
collective/casestudy/profiles.zcml
collective/casestudy/testing.py
collective/casestudy/behaviors/__init__.py
collective/casestudy/behaviors/address_info.py
collective/casestudy/behaviors/configure.zcml
collective/casestudy/behaviors/contact_info.py
collective/casestudy/behaviors/providers.py
collective/casestudy/browser/__init__.py
collective/casestudy/browser/configure.zcml
collective/casestudy/browser/controlpanel.py
collective/casestudy/content/__init__.py
collective/casestudy/content/case_study.py
collective/casestudy/content/provider.py
collective/casestudy/indexers/__init__.py
collective/casestudy/indexers/case_study.py
collective/casestudy/indexers/configure.zcml
collective/casestudy/indexers/providers.py
collective/casestudy/locales/collective.casestudy.pot
collective/casestudy/locales/update.py
collective/casestudy/locales/es/LC_MESSAGES/collective.casestudy.po
collective/casestudy/locales/pt_BR/LC_MESSAGES/collective.casestudy.po
collective/casestudy/profiles/default/browserlayer.xml
collective/casestudy/profiles/default/catalog.xml
collective/casestudy/profiles/default/controlpanel.xml
collective/casestudy/profiles/default/diff_tool.xml
collective/casestudy/profiles/default/metadata.xml
collective/casestudy/profiles/default/repositorytool.xml
collective/casestudy/profiles/default/rolemap.xml
collective/casestudy/profiles/default/types.xml
collective/casestudy/profiles/default/workflows.xml
collective/casestudy/profiles/default/registry/main.xml
collective/casestudy/profiles/default/registry/querystring.xml
collective/casestudy/profiles/default/types/CaseStudy.xml
collective/casestudy/profiles/default/types/Provider.xml
collective/casestudy/profiles/default/workflows/provider_workflow/definition.xml
collective/casestudy/profiles/uninstall/browserlayer.xml
collective.casestudy-1.0.0a3.dist-info/LICENSE.md
collective.casestudy-1.0.0a3.dist-info/METADATA
collective.casestudy-1.0.0a3.dist-info/WHEEL
collective.casestudy-1.0.0a3.dist-info/entry_points.txt
collective.casestudy-1.0.0a3.dist-info/namespace_packages.txt
collective.casestudy-1.0.0a3.dist-info/top_level.txt
collective.casestudy-1.0.0a3.dist-info/zip-safe
collective.casestudy-1.0.0a3.dist-info/RECORD
