Metadata-Version: 2.1
Name: collective.casestudy
Version: 1.0.0a3
Summary: Case Study content type for Plone.
Home-page: https://github.com/collective/collective.casestudy
Author: Plone Community
Author-email: ericof@plone.org
License: GPL version 2
Project-URL: PyPI, https://pypi.python.org/pypi/collective.casestudy
Project-URL: Source, https://github.com/collective/collective.casestudy
Project-URL: Tracker, https://github.com/collective/collective.casestudy/issues
Keywords: Python Plone CMS
Classifier: Development Status :: 5 - Production/Stable
Classifier: Environment :: Web Environment
Classifier: Framework :: Plone
Classifier: Framework :: Plone :: Addon
Classifier: Framework :: Plone :: 6.0
Classifier: Programming Language :: Python
Classifier: Programming Language :: Python :: 3.8
Classifier: Programming Language :: Python :: 3.9
Classifier: Programming Language :: Python :: 3.10
Classifier: Programming Language :: Python :: 3.11
Classifier: Operating System :: OS Independent
Classifier: License :: OSI Approved :: GNU General Public License v2 (GPLv2)
Requires-Python: >=3.8
License-File: LICENSE.md
Requires-Dist: setuptools
Requires-Dist: Plone
Requires-Dist: plone.api
Requires-Dist: pycountry
Provides-Extra: test
Requires-Dist: zest.releaser[recommended] ; extra == 'test'
Requires-Dist: plone.app.testing (>=7.0.0a3) ; extra == 'test'
Requires-Dist: plone.restapi[test] ; extra == 'test'
Requires-Dist: pytest ; extra == 'test'
Requires-Dist: pytest-cov ; extra == 'test'
Requires-Dist: pytest-plone (>=0.2.0) ; extra == 'test'
